Workbook
Name anos: APP!$C$12
Name aporte: APP!$C$11
Name perfil: APP!$C$24
Name salario: APP!$C$6
Name sugestao_aporte: APP!$C$8
Name taxa_mensal: APP!$C$7

Sheet APP
B2: SIMULADOR DE INVESTIMENTOS EM FIIs
B5: CONFIGURAÇÕES
B6: Salário | C6: 3000
B7: Rendimento Carteira | C7: 0.008
B8: Sugestão de Investimento (30%) | C8: =salario*0.3 -> 900
B10: INVESTIMENTO MENSAL
B11: Quanto investir por mês ? | C11: 500
B12: Por quantos anos ? | C12: 5
B13: Taxa de Rendimento mensal ? | C13: =taxa_mensal -> 0.008
B14: Patrimônio acumulado ? | C14: =-FV(taxa_mensal, anos*12, aporte) -> 38311.933
B15: Dividendos Mensais ? | C15: =C14*taxa_mensal -> 306.49547
B17: Cenários | C17: Patrimônio | D17: Dividendo
B18: Quanto em 2 Anos ? | C18: =-FV(taxa_mensal, 2*12, aporte) -> 13171.578 | D18: =C18*taxa_mensal -> 105.37262
B19: Quanto em 5 Anos ? | C19: =-FV(taxa_mensal, 5*12, aporte) -> 38311.933 | D19: =C19*taxa_mensal -> 306.49547
B20: Quanto em 10 Anos ? | C20: =-FV(taxa_mensal, 10*12, aporte) -> 100108.73 | D20: =C20*taxa_mensal -> 800.86988
B21: Quanto em 20 Anos ? | C21: =-FV(taxa_mensal, 20*12, aporte) -> 360565.61 | D21: =C21*taxa_mensal -> 2884.5249
B22: Quanto em 30 Anos ? | C22: =-FV(taxa_mensal, 30*12, aporte) -> 1038206.6 | D22: =C22*taxa_mensal -> 8305.6529
B24: PERFIL | C24: Moderado
B25: VALOR A SER INVESTIDO POR MÊS | C25: =aporte -> 500
B27: TIPO DE FII | C27: Percentual Sugerido | D27: Valores
B28: PAPEL | C28: =VLOOKUP(perfil&B28, Apoio!$C$2:$F$19, 4, FALSE) -> 0.3 | D28: =C28*aporte -> 150
B29: TIJOLO | C29: =VLOOKUP(perfil&B29, Apoio!$C$2:$F$19, 4, FALSE) -> 0.35 | D29: =C29*aporte -> 175
B30: HÍBRIDOS | C30: =VLOOKUP(perfil&B30, Apoio!$C$2:$F$19, 4, FALSE) -> 0.15 | D30: =C30*aporte -> 75
B31: FDFs | C31: =VLOOKUP(perfil&B31, Apoio!$C$2:$F$19, 4, FALSE) -> 0.1 | D31: =C31*aporte -> 50
B32: DESENVOLVIMENTO | C32: =VLOOKUP(perfil&B32, Apoio!$C$2:$F$19, 4, FALSE) -> 0.05 | D32: =C32*aporte -> 25
B33: HOTELARIAS | C33: =VLOOKUP(perfil&B33, Apoio!$C$2:$F$19, 4, FALSE) -> 0.05 | D33: =C33*aporte -> 25
B34: TOTAL | C34: =SUM(C28:C33) -> 1 | D34: =SUM(D28:D33) -> 500

Sheet Apoio
A1: Conservador | C1: Chave | D1: Perfil | E1: Tipo FII | F1: Percentual
A2: Moderado | C2: =D2&E2 -> ConservadorPAPEL | D2: Conservador | E2: PAPEL | F2: 0.4
A3: Arrojado | C3: =D3&E3 -> ConservadorTIJOLO | D3: Conservador | E3: TIJOLO | F3: 0.4
C4: =D4&E4 -> ConservadorHÍBRIDOS | D4: Conservador | E4: HÍBRIDOS | F4: 0.1
C5: =D5&E5 -> ConservadorFDFs | D5: Conservador | E5: FDFs | F5: 0.1
C6: =D6&E6 -> ConservadorDESENVOLVIMENTO | D6: Conservador | E6: DESENVOLVIMENTO | F6: 0
C7: =D7&E7 -> ConservadorHOTELARIAS | D7: Conservador | E7: HOTELARIAS | F7: 0
C8: =D8&E8 -> ModeradoPAPEL | D8: Moderado | E8: PAPEL | F8: 0.3
C9: =D9&E9 -> ModeradoTIJOLO | D9: Moderado | E9: TIJOLO | F9: 0.35
C10: =D10&E10 -> ModeradoHÍBRIDOS | D10: Moderado | E10: HÍBRIDOS | F10: 0.15
C11: =D11&E11 -> ModeradoFDFs | D11: Moderado | E11: FDFs | F11: 0.1
C12: =D12&E12 -> ModeradoDESENVOLVIMENTO | D12: Moderado | E12: DESENVOLVIMENTO | F12: 0.05
C13: =D13&E13 -> ModeradoHOTELARIAS | D13: Moderado | E13: HOTELARIAS | F13: 0.05
C14: =D14&E14 -> ArrojadoPAPEL | D14: Arrojado | E14: PAPEL | F14: 0.2
C15: =D15&E15 -> ArrojadoTIJOLO | D15: Arrojado | E15: TIJOLO | F15: 0.3
... C19: =D19&E19 -> ArrojadoHOTELARIAS | D19: Arrojado | E19: HOTELARIAS | F19: 0.1
